{"rayz": [{"Elo": 3112, "Level": 10}], "rakoN": [{"Elo": 2753, "Level": 10}], "_Rubyi": [{"Elo": 2703, "Level": 10}], "MRxRED": [{"Elo": 2651, "Level": 10}], "ron1N": [{"Elo": 2614, "Level": 10}], "MadMat": [{"Elo": 2578, "Level": 10}], "TstsLikeMeat": [{"Elo": 2453, "Level": 10}], "s1mpMeister": [{"Elo": 2442, "Level": 10}], "-ProToX": [{"Elo": 2437, "Level": 10}], "sefer1999": [{"Elo": 2110, "Level": 10}], "-TobseN-": [{"Elo": 1999, "Level": 9}], "Deu7": [{"Elo": 1996, "Level": 9}], "itsWuyu": [{"Elo": 1989, "Level": 9}], "_DyeknoM": [{"Elo": 1963, "Level": 9}], "ToggleToni": [{"Elo": 1806, "Level": 9}], "DannyDE": [{"Elo": 1405, "Level": 7}], "rabemd": [{"Elo": 1138, "Level": 5}]}